qastle/__init__.py
qastle/ast_util.py
qastle/columns_util.py
qastle/linq_util.py
qastle/parse.py
qastle/syntax.lark
qastle/transform.py
qastle/translate.py
qastle-0.18.1.dist-info/licenses/LICENSE
qastle-0.18.1.dist-info/METADATA
qastle-0.18.1.dist-info/WHEEL
qastle-0.18.1.dist-info/top_level.txt
qastle-0.18.1.dist-info/RECORD
