Metadata-Version: 2.4
Name: qastle
Version: 0.18.1
Summary: Query AST Language Expressions
Home-page: https://github.com/iris-hep/qastle
Author: Mason Proffitt
Author-email: masonlp@uw.edu
Requires-Python: >=3.8, <3.14
License-File: LICENSE
Requires-Dist: lark
Provides-Extra: test
Requires-Dist: flake8; extra == "test"
Requires-Dist: pytest; extra == "test"
Requires-Dist: pytest-cov; extra == "test"
Dynamic: author
Dynamic: author-email
Dynamic: description
Dynamic: description-content-type
Dynamic: home-page
Dynamic: license-file
Dynamic: provides-extra
Dynamic: requires-dist
Dynamic: requires-python
Dynamic: summary
